Workbook
Name Rendimento: 'Página1'!$E$5

Sheet Página1
B2: Configurações
B4: Salario | E4: 1000
B5: Rendimento | E5: 0.006
B6: Quantidade dos aportes | E6: =E4*30% -> 300
B8: Investimento Mensal
B10: Investimento mensal | E10: 500
B11: Tempo de aportes (Anos) | E11: 5
B12: Rendimento mensal | E12: 0.0108
B13: Patrimonio acumulado | E13: =FV(E12,E11*12,E10*-1) -> 41902.01
B14: Investimento mensal | E14: =E13*E5 -> 251.41206
B16: Cenário | F16: Dividendos
B18: Rendimento em 2 | D18: =FV(E12,2*12,$E$10*-1) -> 13615.432 | F18: =(D18*Rendimento) -> 81.692591
B19: Rendimento em 5 | D19: =FV($E$12,5*12,$E$10*-1) -> 41902.01 | F19: =(D19*Rendimento) -> 251.41206
B20: Rendimento em 10 | D20: =FV($E$12,10*12,$E$10*-1) -> 121728.83 | F20: =(D20*Rendimento) -> 730.373
B21: Rendimento em 15 | D21: =FV($E$12,15*12,$E$10*-1) -> 273805.59 | F21: =(D21*Rendimento) -> 1642.8335
B22: Rendimento em 20 | D22: =FV($E$12,20*12,$E$10*-1) -> 563524.5 | F22: =(D22*Rendimento) -> 3381.147
B23: Rendimento em 30 | D23: =FV($E$12,30*12,$E$10*-1) -> 2166952.4 | F23: =(D23*Rendimento) -> 13001.714
B25: Perfil | E25: Agressivo
B26: Valor a ser investido por mes | E26: =E6 -> 300
B27: Tipo de FIIs | E27: Percentual sugerido | F27: Valores
B28: Papel | E28: =VLOOKUP($E$25&"-"&B28,'Página2'!A:D,4,FALSE()) -> 0.5 | F28: =E28*$E$26 -> 150
B29: Tijolo | E29: =VLOOKUP($E$25&"-"&B29,'Página2'!A:D,4,FALSE()) -> 0.1 | F29: =E29*$E$26 -> 30
B30: hibrido | E30: =VLOOKUP($E$25&"-"&B30,'Página2'!A:D,4,FALSE()) -> 0.05 | F30: =E30*$E$26 -> 15
B31: FOFs | E31: =VLOOKUP($E$25&"-"&B31,'Página2'!A:D,4,FALSE()) -> 0.05 | F31: =E31*$E$26 -> 15
B32: desenvolvimento | E32: =VLOOKUP($E$25&"-"&B32,'Página2'!A:D,4,FALSE()) -> 0.2 | F32: =E32*$E$26 -> 60
B33: Hotelaria | E33: =VLOOKUP($E$25&"-"&B33,'Página2'!A:D,4,FALSE()) -> 0.1 | F33: =E33*$E$26 -> 30

Sheet Página2
A1: Chave | B1: Perfil | C1: Tipos de FIIs
A2: =B2&"-"&C2 -> Conservador-Papel | B2: Conservador | C2: Papel | D2: 0.3
A3: =B3&"-"&C3 -> Conservador-Tijolo | B3: Conservador | C3: Tijolo | D3: 0.5 | G3: %
A4: =B4&"-"&C4 -> Conservador-hibrido | B4: Conservador | C4: hibrido | D4: 0.1 | F4: Moderado-hibrido | G4: =VLOOKUP(F4,$A:$D,4,FALSE()) -> 0.08
A5: =B5&"-"&C5 -> Conservador-FOFs | B5: Conservador | C5: FOFs | D5: 0.1
A6: =B6&"-"&C6 -> Conservador-desenvolvimento | B6: Conservador | C6: desenvolvimento | D6: 0
A7: =B7&"-"&C7 -> Conservador-Hotelaria | B7: Conservador | C7: Hotelaria | D7: 0
A9: =B9&"-"&C9 -> Moderado-Papel | B9: Moderado | C9: Papel | D9: 0.32
A10: =B10&"-"&C10 -> Moderado-Tijolo | B10: Moderado | C10: Tijolo | D10: 0.4
A11: =B11&"-"&C11 -> Moderado-hibrido | B11: Moderado | C11: hibrido | D11: 0.08
A12: =B12&"-"&C12 -> Moderado-FOFs | B12: Moderado | C12: FOFs | D12: 0.1
A13: =B13&"-"&C13 -> Moderado-desenvolvimento | B13: Moderado | C13: desenvolvimento | D13: 0.1
A14: =B14&"-"&C14 -> Moderado-Hotelaria | B14: Moderado | C14: Hotelaria | D14: 0.1
A16: =B16&"-"&C16 -> Agressivo-Papel | B16: Agressivo | C16: Papel | D16: 0.5
A17: =B17&"-"&C17 -> Agressivo-Tijolo | B17: Agressivo | C17: Tijolo | D17: 0.1
A18: =B18&"-"&C18 -> Agressivo-hibrido | B18: Agressivo | C18: hibrido | D18: 0.05
... A21: =B21&"-"&C21 -> Agressivo-Hotelaria | B21: Agressivo | C21: Hotelaria | D21: 0.1
